{"legislative_session": "2026", "identifier": "HB 2296", "title": "Creates provisions relating to insurance coverage of alternatives to opioid drugs", "from_organization": "~{\"classification\": \"lower\"}", "classification": ["bill"], "subject": ["DRUGS AND CONTROLLED SUBSTANCES", "INSURANCE - HEALTH"], "abstracts": [], "other_titles": [{"note": "official", "title": "HB 2296"}], "other_identifiers": [], "actions": [{"description": "Prefiled (H)", "date": "2025-12-09T06:00:00+00:00", "organization_id": "~{\"classification\": \"lower\"}", "classification": [], "related_entities": []}], "sponsorships": [{"name": "Kent Haden", "classification": "primary", "entity_type": "person", "primary": true, "person_id": "~{\"name\": \"Kent Haden\"}", "organization_id": null}], "related_bills": [], "versions": [{"note": "Introduced", "links": [{"url": "https://documents.house.mo.gov/billtracking/bills261/hlrbillspdf/5476H.01I.pdf", "media_type": "application/pdf"}], "date": "", "classification": ""}], "documents": [], "citations": [], "sources": [{"url": "https://www.house.mo.gov/BillContent.aspx?bill=HB2296&year=2026&code=R&style=new", "note": ""}, {"url": "https://house.mo.gov/billactions.aspx?bill=HB2296&year=2026&code=R", "note": ""}], "extras": {}, "jurisdiction": {"id": "ocd-jurisdiction/country:us/state:mo/government", "name": "Missouri", "classification": "state", "division_id": "ocd-division/country:us/state:mo"}, "scraped_at": "2025-12-23T09:20:27+00:00", "_id": "9e9f06f4-dfe0-11f0-a9d6-964bf561b638"}