{"legislative_session": "2026", "identifier": "HB 2034", "title": "Creates provisions relating to insurance coverage of orthotic, prosthetic, and assistive devices", "from_organization": "~{\"classification\": \"lower\"}", "classification": ["bill"], "subject": ["DISABILITIES", "HEALTH CARE", "INSURANCE - HEALTH"], "abstracts": [], "other_titles": [{"note": "official", "title": "HB 2034"}], "other_identifiers": [], "actions": [{"description": "Prefiled (H)", "date": "2025-12-01T06:00:00+00:00", "organization_id": "~{\"classification\": \"lower\"}", "classification": [], "related_entities": []}], "sponsorships": [{"name": "Carolyn Caton", "classification": "primary", "entity_type": "person", "primary": true, "person_id": "~{\"name\": \"Carolyn Caton\"}", "organization_id": null}], "related_bills": [], "versions": [{"note": "Introduced", "links": [{"url": "https://documents.house.mo.gov/billtracking/bills261/hlrbillspdf/3872H.01I.pdf", "media_type": "application/pdf"}], "date": "", "classification": ""}], "documents": [], "citations": [], "sources": [{"url": "https://www.house.mo.gov/BillContent.aspx?bill=HB2034&year=2026&code=R&style=new", "note": ""}, {"url": "https://house.mo.gov/billactions.aspx?bill=HB2034&year=2026&code=R", "note": ""}], "extras": {}, "jurisdiction": {"id": "ocd-jurisdiction/country:us/state:mo/government", "name": "Missouri", "classification": "state", "division_id": "ocd-division/country:us/state:mo"}, "scraped_at": "2025-12-29T09:18:29+00:00", "_id": "56b41d64-e497-11f0-bfea-0a4e8391cdeb"}