{"legislative_session": "2026", "identifier": "SB 1249", "title": "Allows the Director of Public Safety to deny certain individuals a peace officer license or entry into basic training courses", "from_organization": "~{\"classification\": \"upper\"}", "classification": ["bill"], "subject": [], "abstracts": [{"note": "abstract", "abstract": "Allows the Director of Public Safety to deny certain individuals a peace officer license or entry into basic training courses"}], "other_titles": [], "other_identifiers": [], "actions": [{"description": "Prefiled", "date": "2025-12-01T06:00:00+00:00", "organization_id": "~{\"classification\": \"upper\"}", "classification": [], "related_entities": []}], "sponsorships": [{"name": "Gregory (15)", "classification": "primary", "entity_type": "person", "primary": true, "person_id": "~{\"name\": \"Gregory (15)\"}", "organization_id": null}], "related_bills": [], "versions": [], "documents": [], "citations": [], "sources": [{"url": "http://www.senate.mo.gov/26info/BTS_Web/Bill.aspx?SessionType=R&BillID=459", "note": ""}, {"url": "https://www.senate.mo.gov/26info/BTS_Web/Actions.aspx?SessionType=R&BillID=459", "note": ""}, {"url": "https://www.senate.mo.gov/26info/BTS_Web/BillText.aspx?SessionType=R&BillID=459", "note": ""}], "extras": {}, "jurisdiction": {"id": "ocd-jurisdiction/country:us/state:mo/government", "name": "Missouri", "classification": "state", "division_id": "ocd-division/country:us/state:mo"}, "scraped_at": "2025-12-11T21:54:57+00:00", "_id": "07a3eab0-d6dc-11f0-a9ee-32cd2fe69806"}