{"legislative_session": "2026", "identifier": "HB 2304", "title": "Establishes written parental consent requirements for individualized education programs (IEPs)", "from_organization": "~{\"classification\": \"lower\"}", "classification": ["bill"], "subject": ["DISABILITIES", "EDUCATION, ELEMENTARY AND SECONDARY", "ELEMENTARY AND SECONDARY EDUCATION, DEPT. OF"], "abstracts": [], "other_titles": [{"note": "official", "title": "HB 2304"}], "other_identifiers": [], "actions": [{"description": "Prefiled (H)", "date": "2025-12-09T06:00:00+00:00", "organization_id": "~{\"classification\": \"lower\"}", "classification": [], "related_entities": []}], "sponsorships": [{"name": "Philip Oehlerking", "classification": "primary", "entity_type": "person", "primary": true, "person_id": "~{\"name\": \"Philip Oehlerking\"}", "organization_id": null}, {"name": "Colin Wellenkamp", "classification": "cosponsor", "entity_type": "person", "primary": false, "person_id": "~{\"name\": \"Colin Wellenkamp\"}", "organization_id": null}, {"name": "Tricia Byrnes", "classification": "cosponsor", "entity_type": "person", "primary": false, "person_id": "~{\"name\": \"Tricia Byrnes\"}", "organization_id": null}, {"name": "Dave Hinman", "classification": "cosponsor", "entity_type": "person", "primary": false, "person_id": "~{\"name\": \"Dave Hinman\"}", "organization_id": null}], "related_bills": [], "versions": [{"note": "Introduced", "links": [{"url": "https://documents.house.mo.gov/billtracking/bills261/hlrbillspdf/5785H.01I.pdf", "media_type": "application/pdf"}], "date": "", "classification": ""}], "documents": [], "citations": [], "sources": [{"url": "https://www.house.mo.gov/BillContent.aspx?bill=HB2304&year=2026&code=R&style=new", "note": ""}, {"url": "https://house.mo.gov/billactions.aspx?bill=HB2304&year=2026&code=R", "note": ""}], "extras": {}, "jurisdiction": {"id": "ocd-jurisdiction/country:us/state:mo/government", "name": "Missouri", "classification": "state", "division_id": "ocd-division/country:us/state:mo"}, "scraped_at": "2025-12-23T09:20:35+00:00", "_id": "a36561ce-dfe0-11f0-a9d6-964bf561b638"}